[
  {
    "review_id": "14218612270",
    "app_id": "com.kbankwith.smartbank",
    "app_name": "케이뱅크",
    "store_id": "1178872627",
    "source": "app_store",
    "country": "kr",
    "rating": 1.0,
    "review_text": "설사를 싸라.. 별 지랄을 다함ㅋ 우엑 지랄 고만 떨어요 케이뱅크 , 내가 이래서 KT를 안씀 ㅇㅇㅇ 다른 통신사 꺼 쓰지 차라리 \n\n26년 6월 24\n지랄 고만 떨어요 케이뱅크 ~~ 죽여버리기 전에 , 살인충동 들어",
    "date": "2026-06-23",
    "userName": "ㅎl나"
  },
  {
    "review_id": "14218564144",
    "app_id": "com.kbankwith.smartbank",
    "app_name": "케이뱅크",
    "store_id": "1178872627",
    "source": "app_store",
    "country": "kr",
    "rating": 5.0,
    "review_text": "너무간편하네요 굿",
    "date": "2026-06-23",
    "userName": "핵사이다뽀롱"
  },
  {
    "review_id": "14216549586",
    "app_id": "com.kbankwith.smartbank",
    "app_name": "케이뱅크",
    "store_id": "1178872627",
    "source": "app_store",
    "country": "kr",
    "rating": 3.0,
    "review_text": "최근에 앱이 잘 안열려서 리뷰 봤는데 저만 그런게 아니네요 ㅠ",
    "date": "2026-06-23",
    "userName": "개화나네;"
  },
  {
    "review_id": "14207205625",
    "app_id": "com.kbankwith.smartbank",
    "app_name": "케이뱅크",
    "store_id": "1178872627",
    "source": "app_store",
    "country": "kr",
    "rating": 2.0,
    "review_text": "새로 바뀐 앱 아이콘 정말정말 못 생겼습니다. 앱 지워버리고 싶을 정도로 못 생겼습니다. 디자인팀이란 게 없나요? 너무하네요.",
    "date": "2026-06-20",
    "userName": "멍뭉아산책가자"
  },
  {
    "review_id": "14204582833",
    "app_id": "com.kbankwith.smartbank",
    "app_name": "케이뱅크",
    "store_id": "1178872627",
    "source": "app_store",
    "country": "kr",
    "rating": 5.0,
    "review_text": "very Gooooooooood",
    "date": "2026-06-20",
    "userName": "낭만농사꾼"
  },
  {
    "review_id": "14196085998",
    "app_id": "com.kbankwith.smartbank",
    "app_name": "케이뱅크",
    "store_id": "1178872627",
    "source": "app_store",
    "country": "kr",
    "rating": 1.0,
    "review_text": "치가 떨린다",
    "date": "2026-06-17",
    "userName": "ㄸㄷㄹㄹ"
  },
  {
    "review_id": "14195533386",
    "app_id": "com.kbankwith.smartbank",
    "app_name": "케이뱅크",
    "store_id": "1178872627",
    "source": "app_store",
    "country": "kr",
    "rating": 5.0,
    "review_text": "굿",
    "date": "2026-06-17",
    "userName": "카론44"
  },
  {
    "review_id": "14195434590",
    "app_id": "com.kbankwith.smartbank",
    "app_name": "케이뱅크",
    "store_id": "1178872627",
    "source": "app_store",
    "country": "kr",
    "rating": 1.0,
    "review_text": "아니 토스나 카벵 열릴때 케이뱅크는 렉 ㅈㄴ 걸리면서 안열리고 뭔 탭을 하면 쳐 열린대요 개선좀 해주세요 앱 안열려서 밖에선 뭐 결제도 못해",
    "date": "2026-06-17",
    "userName": "케이뱅크 개선해라"
  },
  {
    "review_id": "14192819950",
    "app_id": "com.kbankwith.smartbank",
    "app_name": "케이뱅크",
    "store_id": "1178872627",
    "source": "app_store",
    "country": "kr",
    "rating": 1.0,
    "review_text": "기종:아이폰12\n버전:IOS26.5\n다른 앱들 비해서 느리고 버벅됩니다.\n앱 관리 하시나요?\n책상에 앉아서 시간만 떼우지 마시고 앱 관리좀 하세요!\n왜 케이뱅크만 그러는지 모르겠네요!\n동영상 첨부 할수 있으면 좋을텐테....",
    "date": "2026-06-17",
    "userName": "승민83"
  },
  {
    "review_id": "14191175948",
    "app_id": "com.kbankwith.smartbank",
    "app_name": "케이뱅크",
    "store_id": "1178872627",
    "source": "app_store",
    "country": "kr",
    "rating": 3.0,
    "review_text": "앱이 잘 안열여요",
    "date": "2026-06-16",
    "userName": "오로지 포인트"
  },
  {
    "review_id": "14185336363",
    "app_id": "com.kbankwith.smartbank",
    "app_name": "케이뱅크",
    "store_id": "1178872627",
    "source": "app_store",
    "country": "kr",
    "rating": 5.0,
    "review_text": "모바일 뱅킹 편리해요",
    "date": "2026-06-15",
    "userName": "포켓보스"
  },
  {
    "review_id": "14173997770",
    "app_id": "com.kbankwith.smartbank",
    "app_name": "케이뱅크",
    "store_id": "1178872627",
    "source": "app_store",
    "country": "kr",
    "rating": 1.0,
    "review_text": "접속만 하면 오류가 발생했어요 잠시후 다시 시도해주세요 오늘 하루종일 계속 뜨는데 왜그러는거죠? 그래서 잔고 확인이 안돼요ㅠ",
    "date": "2026-06-12",
    "userName": "코인주세요ㅜㅜ"
  },
  {
    "review_id": "14164987576",
    "app_id": "com.kbankwith.smartbank",
    "app_name": "케이뱅크",
    "store_id": "1178872627",
    "source": "app_store",
    "country": "kr",
    "rating": 1.0,
    "review_text": "Vpn을 사용 못하게 막을 거면 해외에서 접속이 가능하게 해놓든가 둘 다 못하게 막으면 어떻게 쓰라는 건가요? 고객센터는 안받고, 카톡은 앱으로 연결해놔서 결국 또 못쓰고. 결국 토스로 하루에 야금야금 빼와야 하는게 어이없어서 남깁니다. 기획자가 해외에 나가본 적이 없는 건지",
    "date": "2026-06-09",
    "userName": "Uriejndndkx"
  },
  {
    "review_id": "14161608201",
    "app_id": "com.kbankwith.smartbank",
    "app_name": "케이뱅크",
    "store_id": "1178872627",
    "source": "app_store",
    "country": "kr",
    "rating": 5.0,
    "review_text": "긴급자금수혈이 필요했는데 몇분만에 뚝딱\n\n감사합니다",
    "date": "2026-06-09",
    "userName": "하나공여섯"
  },
  {
    "review_id": "14159906864",
    "app_id": "com.kbankwith.smartbank",
    "app_name": "케이뱅크",
    "store_id": "1178872627",
    "source": "app_store",
    "country": "kr",
    "rating": 1.0,
    "review_text": "사용할수록 불쾌하고 불편하고 좃같음",
    "date": "2026-06-08",
    "userName": "라저갓"
  },
  {
    "review_id": "14153856725",
    "app_id": "com.kbankwith.smartbank",
    "app_name": "케이뱅크",
    "store_id": "1178872627",
    "source": "app_store",
    "country": "kr",
    "rating": 5.0,
    "review_text": "편리하고 사용하기 편리해요",
    "date": "2026-06-07",
    "userName": "윤슬이님"
  },
  {
    "review_id": "14146334086",
    "app_id": "com.kbankwith.smartbank",
    "app_name": "케이뱅크",
    "store_id": "1178872627",
    "source": "app_store",
    "country": "kr",
    "rating": 1.0,
    "review_text": "버스탈때 계속 안 찍혀서 5분만에 찍혔네요",
    "date": "2026-06-05",
    "userName": "bz_dhxn"
  },
  {
    "review_id": "14141870652",
    "app_id": "com.kbankwith.smartbank",
    "app_name": "케이뱅크",
    "store_id": "1178872627",
    "source": "app_store",
    "country": "kr",
    "rating": 1.0,
    "review_text": "다른 어떤 타행사은행어플보다도 오류 자주뜹니다. 상담사항 연결할때 전화문의가 안되면 톡상담이라도 제대로 연결되게 하셔야죠~ 어플이 오류인데 어플에 들어가지지도 않으면 톡상담 자체가 안되게 설정되어있면 바쁜사람들은 수십명 대기중인 전화상담으로만 해결하게 되어있고... 참... 이렇게 리뷰에 구구절절 남기기도 난생처음이네요. 별점도 0점 주려다가 0점이면 리뷰자체도 안써지게 되어있어서 1점 드립니다.",
    "date": "2026-06-03",
    "userName": "오플오류"
  },
  {
    "review_id": "14141387075",
    "app_id": "com.kbankwith.smartbank",
    "app_name": "케이뱅크",
    "store_id": "1178872627",
    "source": "app_store",
    "country": "kr",
    "rating": 1.0,
    "review_text": "업비트도 케이벵크도 개판이구먼",
    "date": "2026-06-03",
    "userName": "오비오비오비 오오비~ 승리의 이름"
  },
  {
    "review_id": "14137646462",
    "app_id": "com.kbankwith.smartbank",
    "app_name": "케이뱅크",
    "store_id": "1178872627",
    "source": "app_store",
    "country": "kr",
    "rating": 1.0,
    "review_text": "특수문자정보등록불가대체뭔데 아진짜",
    "date": "2026-06-02",
    "userName": "양산개장수"
  },
  {
    "review_id": "14135223505",
    "app_id": "com.kbankwith.smartbank",
    "app_name": "케이뱅크",
    "store_id": "1178872627",
    "source": "app_store",
    "country": "kr",
    "rating": 5.0,
    "review_text": "처음 거래인데 수수료 없어 좋아요",
    "date": "2026-06-02",
    "userName": "운림동"
  },
  {
    "review_id": "14134184650",
    "app_id": "com.kbankwith.smartbank",
    "app_name": "케이뱅크",
    "store_id": "1178872627",
    "source": "app_store",
    "country": "kr",
    "rating": 1.0,
    "review_text": "제목 그대로에요. 업데이트하고 나서 접속이 안돼요",
    "date": "2026-06-01",
    "userName": "Park Jeong Shik"
  },
  {
    "review_id": "14134178253",
    "app_id": "com.kbankwith.smartbank",
    "app_name": "케이뱅크",
    "store_id": "1178872627",
    "source": "app_store",
    "country": "kr",
    "rating": 5.0,
    "review_text": "알파카드를 해지하고 새 입출금통장 카드를 만들었는데 해지된 알파카드에 충전된 교통비는 어떻게 되는건가요?",
    "date": "2026-06-01",
    "userName": "급함요"
  },
  {
    "review_id": "14133796752",
    "app_id": "com.kbankwith.smartbank",
    "app_name": "케이뱅크",
    "store_id": "1178872627",
    "source": "app_store",
    "country": "kr",
    "rating": 1.0,
    "review_text": "은행의 기본은 입출금, 입출금한 내역에 대한 올바른 표기이다\n\n나는 21세기 은행어플에서\n\n기원전 이집트에 음료수팔이보다 부정확한 입출금 내역을 표시한다는게 믿기지가 않는다\n\n심지어 이메일로 출력을 해도 기존 내역만 나온다\n\n그나마 다행인건 잔고는 정확하게 표시가 된다는것\n\n상담원의 대답은 더 가관이다\n- 날짜 설정을 잘못하신거 아닌가요?\n\n나는 혹시라도 내가 미국에 거주중이라 날짜가 안맞아서 그런가 싶어서 상담원의 전화를 받으며 날짜 설정을 찾아보았다\n\n보편적인 인간의 지능을 가졌더라면 당연히 앱을 사용하는 시점에 거래내역이 가장 최상단에 위치하게 만들테지만 혹시나 하는 마음에 찾아봤지만 당연히 그런 설정은 없었고 앱에 문제가 있는것 같다고 말씀하시는데 \n\n그렇다면 1개월 치 거래내역을 출력을 눌러서 메일로 받은 곳 역시 엉뚱한 거래내역을 출력중인데\n거래내역을 내 앱의 저장된 거래내역을 출력하는건가?\n원본를 기록하는 서버는 없는건가?\n\n그냥 너무나 놀라운 고객지원과\n놀라운 서비스에 당연히 보안 역시 위험할께 불보듯 뻔하니 탈퇴를 하고 싶지만 업비트를 사용하려면 계속\n써야한다는 사실이 날 너무 슬프게 만든다\n\n정말로 업비트와 케이뱅크가 결별하거나\n새로운 은행이 개설되고 입출금 창구에서만 입출금이 된다고 해도 거기로 이동하고 싶다\n\n하나를 보면 열을 안다고\n이런 은행에 내 소중한 개인정보가 저장되어 있다는 사실이 너무나 안타깝다\n\n하지만 실낱같은 희망으로\n개인정보조차 재대로 저장을 못해서\n어쩌면 해커들도 내 개인정보를 못찾을수도 있다는 사실에 아주 약간의 희망은 가지고 있다",
    "date": "2026-06-01",
    "userName": "레몬쓰레기"
  },
  {
    "review_id": "14132912381",
    "app_id": "com.kbankwith.smartbank",
    "app_name": "케이뱅크",
    "store_id": "1178872627",
    "source": "app_store",
    "country": "kr",
    "rating": 2.0,
    "review_text": "너무 느려요 어쩔때는 메인화면 뜰때까지 2분씩이나 걸려요 급하게 이체할일 있으면 속터집니다",
    "date": "2026-06-01",
    "userName": "ㅇㅂ디ㅡㅋㄱ"
  },
  {
    "review_id": "14131174780",
    "app_id": "com.kbankwith.smartbank",
    "app_name": "케이뱅크",
    "store_id": "1178872627",
    "source": "app_store",
    "country": "kr",
    "rating": 1.0,
    "review_text": "왜이러는건데요 앱 삭제하고 별짓 다했는데ㅡㅡ 아 내가 내통장 쓰지도못하고ㅡㅡ 빨리 해결해주세요",
    "date": "2026-06-01",
    "userName": "최구최구짱이짱"
  },
  {
    "review_id": "14129489718",
    "app_id": "com.kbankwith.smartbank",
    "app_name": "케이뱅크",
    "store_id": "1178872627",
    "source": "app_store",
    "country": "kr",
    "rating": 5.0,
    "review_text": "리뷰 최신순 기준 아래아래아래있는 분 리뷰 너무 공감됨\n상단 팝업들(수신동의안내, 이자, 리워드 등)이 한꺼번에 뜨는게 아니라 시간차로 뜨니까 계좌나 메뉴 누를 때 화면이 아래로 밀려서 매번 원하는게 아닌 다른게 눌러져서 꽤나 스트레스입니다\n그거 다 뜰 때까지 1-2초 기다리는 것도 너무 길 때가 있어요\n한꺼번에 뜨도록 바뀌었으면 더 편리할 것 같습니다\n그 외엔 모두 만족합니다.",
    "date": "2026-05-31",
    "userName": "별명생성솜노트업그레이드"
  },
  {
    "review_id": "14124266555",
    "app_id": "com.kbankwith.smartbank",
    "app_name": "케이뱅크",
    "store_id": "1178872627",
    "source": "app_store",
    "country": "kr",
    "rating": 5.0,
    "review_text": "너무 편하고 너무 좋아요",
    "date": "2026-05-30",
    "userName": "신짜로"
  },
  {
    "review_id": "14117813738",
    "app_id": "com.kbankwith.smartbank",
    "app_name": "케이뱅크",
    "store_id": "1178872627",
    "source": "app_store",
    "country": "kr",
    "rating": 1.0,
    "review_text": "켰을때 오류가 안나는 적이 없고 이번에도 돈 빼는데 2시간이나 걸렸음",
    "date": "2026-05-28",
    "userName": "감자맨입니다"
  },
  {
    "review_id": "14116496641",
    "app_id": "com.kbankwith.smartbank",
    "app_name": "케이뱅크",
    "store_id": "1178872627",
    "source": "app_store",
    "country": "kr",
    "rating": 1.0,
    "review_text": "기록 남기는거 싫어해서 리뷰 같은거 안쓰는데 이건 남겨야겠습니다. 매번 앱 켤때마다 뜨는 귀사 상품 홍보 팝업에 끄고 금액 확인 할려고 하거나 다른 기능 누를려고 클릭하면 기다렸다는듯이 상단 또 다른 광고가 그제서야 쳐 뜨면서 광고창으로 넘어가는데 일주일동안 안보기? 일주일 동안 안보겠다고 켤때마다 다른 광고뜨는거 계속 꺼도 또 다른광고로 팝업뜨고 버튼 누를려 하면 다른 광고 로딩 다 됐다고 그제서야 뜨면서 창이 밀리고 광고창이 눌리면서 사파리가 켜지는데 진짜 비속어가 안나올수가 없습니다. 하루이틀도 아니고 케이뱅크 넘어와서 쓰는 2년 내내 이러는데 이거 때문에 은행 옮깁니다 수고하세요",
    "date": "2026-05-28",
    "userName": "ddddiro"
  },
  {
    "review_id": "14114827874",
    "app_id": "com.kbankwith.smartbank",
    "app_name": "케이뱅크",
    "store_id": "1178872627",
    "source": "app_store",
    "country": "kr",
    "rating": 2.0,
    "review_text": "파킹통장 급하게 쓸려고 하면 다른 은행 어플은 잘 터지는데 얘는 계속 안열림 ㅡㅡ",
    "date": "2026-05-28",
    "userName": "kkkkiriiiiii"
  }
]